tests/__init__.py
tests/test_quotes.py
tools/dumpdiffs.py
tools/dumptexts.py
tools/remove-prefixes.py
wpm/__init__.py
wpm/__main__.py
wpm/commandline.py
wpm/config.py
wpm/convert.py
wpm/devfeature.py
wpm/difficulty.py
wpm/error.py
wpm/game.py
wpm/gauss.py
wpm/histogram.py
wpm/quotes.py
wpm/record.py
wpm/screen.py
wpm/stats.py
wpmx-0.1.0.dist-info/licenses/LICENSE.txt
wpmx-0.1.0.dist-info/METADATA
wpmx-0.1.0.dist-info/WHEEL
wpmx-0.1.0.dist-info/entry_points.txt
wpmx-0.1.0.dist-info/top_level.txt
wpmx-0.1.0.dist-info/RECORD
